{
  "DefensiveReboundsA": 25,
  "OffensiveReboundsB": 9,
  "OffensiveReboundsA": 8,
  "DefensiveReboundsB": 16,
  "TurnoversStartersA": 8,
  "TurnoversBenchA": 2,
  "TurnoversStartersB": 8,
  "TurnoversBenchB": 4,
  "StealsStartersA": 4,
  "StealsBenchA": 3,
  "StealsStartersB": 1,
  "StealsBenchB": 3,
  "AssistsStartersA": 18,
  "AssistsBenchA": 14,
  "AssistsStartersB": 15,
  "AssistsBenchB": 9,
  "PointsStartersA": 67,
  "PointsBenchA": 45,
  "PointsStartersB": 43,
  "PointsBenchB": 46,
  "maxA": 14,
  "minutePrevA": 22,
  "prevA": "52-51",
  "minuteStrA": 24,
  "strA": "66-51",
  "maxB": 6,
  "minutePrevB": 14,
  "prevB": "40-30",
  "minuteStrB": 15,
  "strB": "40-36",
  "maxLeadA": 27,
  "maxLeadB": 3,
  "minuteMaxLeadA": 39,
  "minuteMaxLeadB": 19,
  "puntosMaxLeadA": "112-85",
  "puntosMaxLeadB": "45-48",
  "minutoActual": 1,
  "isLive": false
}