{
  "DefensiveReboundsA": 22,
  "OffensiveReboundsB": 11,
  "OffensiveReboundsA": 13,
  "DefensiveReboundsB": 24,
  "TurnoversStartersA": 4,
  "TurnoversBenchA": 1,
  "TurnoversStartersB": 11,
  "TurnoversBenchB": 6,
  "StealsStartersA": 5,
  "StealsBenchA": 2,
  "StealsStartersB": 1,
  "StealsBenchB": 2,
  "AssistsStartersA": 13,
  "AssistsBenchA": 15,
  "AssistsStartersB": 10,
  "AssistsBenchB": 7,
  "PointsStartersA": 42,
  "PointsBenchA": 51,
  "PointsStartersB": 44,
  "PointsBenchB": 30,
  "maxA": 10,
  "minutePrevA": 15,
  "prevA": "32-34",
  "minuteStrA": 18,
  "strA": "42-34",
  "maxB": 10,
  "minutePrevB": 5,
  "prevB": "13-10",
  "minuteStrB": 9,
  "strB": "13-20",
  "maxLeadA": 26,
  "maxLeadB": 11,
  "minuteMaxLeadA": 35,
  "minuteMaxLeadB": 11,
  "puntosMaxLeadA": "91-65",
  "puntosMaxLeadB": "18-29",
  "minutoActual": 1,
  "isLive": false
}