{
  "DefensiveReboundsA": 29,
  "OffensiveReboundsB": 14,
  "OffensiveReboundsA": 8,
  "DefensiveReboundsB": 25,
  "TurnoversStartersA": 6,
  "TurnoversBenchA": 11,
  "TurnoversStartersB": 8,
  "TurnoversBenchB": 9,
  "StealsStartersA": 5,
  "StealsBenchA": 4,
  "StealsStartersB": 8,
  "StealsBenchB": 3,
  "AssistsStartersA": 8,
  "AssistsBenchA": 14,
  "AssistsStartersB": 13,
  "AssistsBenchB": 7,
  "PointsStartersA": 41,
  "PointsBenchA": 64,
  "PointsStartersB": 74,
  "PointsBenchB": 27,
  "maxA": 8,
  "minutePrevA": 4,
  "prevA": "5-11",
  "minuteStrA": 6,
  "strA": "13-11",
  "maxB": 11,
  "minutePrevB": 6,
  "prevB": "13-11",
  "minuteStrB": 9,
  "strB": "13-22",
  "maxLeadA": 7,
  "maxLeadB": 13,
  "minuteMaxLeadA": 43,
  "minuteMaxLeadB": 25,
  "puntosMaxLeadA": "103-96",
  "puntosMaxLeadB": "55-68",
  "minutoActual": 1,
  "isLive": false
}