{
  "DefensiveReboundsA": 26,
  "OffensiveReboundsB": 11,
  "OffensiveReboundsA": 9,
  "DefensiveReboundsB": 31,
  "TurnoversStartersA": 6,
  "TurnoversBenchA": 3,
  "TurnoversStartersB": 10,
  "TurnoversBenchB": 3,
  "StealsStartersA": 6,
  "StealsBenchA": 1,
  "StealsStartersB": 3,
  "StealsBenchB": 1,
  "AssistsStartersA": 8,
  "AssistsBenchA": 11,
  "AssistsStartersB": 18,
  "AssistsBenchB": 0,
  "PointsStartersA": 41,
  "PointsBenchA": 40,
  "PointsStartersB": 62,
  "PointsBenchB": 11,
  "maxA": 12,
  "minutePrevA": 8,
  "prevA": "14-15",
  "minuteStrA": 12,
  "strA": "26-15",
  "maxB": 17,
  "minutePrevB": 20,
  "prevB": "48-33",
  "minuteStrB": 26,
  "strB": "48-50",
  "maxLeadA": 15,
  "maxLeadB": 3,
  "minuteMaxLeadA": 20,
  "minuteMaxLeadB": 6,
  "puntosMaxLeadA": "48-33",
  "puntosMaxLeadB": "10-13",
  "minutoActual": 1,
  "isLive": false
}