{
  "DefensiveReboundsA": 18,
  "OffensiveReboundsB": 8,
  "OffensiveReboundsA": 15,
  "DefensiveReboundsB": 26,
  "TurnoversStartersA": 8,
  "TurnoversBenchA": 3,
  "TurnoversStartersB": 2,
  "TurnoversBenchB": 5,
  "StealsStartersA": 5,
  "StealsBenchA": 1,
  "StealsStartersB": 4,
  "StealsBenchB": 3,
  "AssistsStartersA": 6,
  "AssistsBenchA": 3,
  "AssistsStartersB": 10,
  "AssistsBenchB": 10,
  "PointsStartersA": 59,
  "PointsBenchA": 10,
  "PointsStartersB": 58,
  "PointsBenchB": 41,
  "maxA": 8,
  "minutePrevA": 1,
  "prevA": "0-4",
  "minuteStrA": 4,
  "strA": "8-4",
  "maxB": 9,
  "minutePrevB": 26,
  "prevB": "46-54",
  "minuteStrB": 28,
  "strB": "46-63",
  "maxLeadA": 5,
  "maxLeadB": 32,
  "minuteMaxLeadA": 13,
  "minuteMaxLeadB": 40,
  "puntosMaxLeadA": "25-20",
  "puntosMaxLeadB": "67-99",
  "minutoActual": 1,
  "isLive": false
}