{
  "DefensiveReboundsA": 24,
  "OffensiveReboundsB": 9,
  "OffensiveReboundsA": 15,
  "DefensiveReboundsB": 23,
  "TurnoversStartersA": 6,
  "TurnoversBenchA": 3,
  "TurnoversStartersB": 3,
  "TurnoversBenchB": 4,
  "StealsStartersA": 3,
  "StealsBenchA": 0,
  "StealsStartersB": 4,
  "StealsBenchB": 3,
  "AssistsStartersA": 12,
  "AssistsBenchA": 8,
  "AssistsStartersB": 17,
  "AssistsBenchB": 4,
  "PointsStartersA": 47,
  "PointsBenchA": 30,
  "PointsStartersB": 44,
  "PointsBenchB": 36,
  "maxA": 7,
  "minutePrevA": 25,
  "prevA": "46-44",
  "minuteStrA": 26,
  "strA": "53-44",
  "maxB": 9,
  "minutePrevB": 30,
  "prevB": "60-54",
  "minuteStrB": 31,
  "strB": "60-63",
  "maxLeadA": 10,
  "maxLeadB": 8,
  "minuteMaxLeadA": 28,
  "minuteMaxLeadB": 8,
  "puntosMaxLeadA": "56-46",
  "puntosMaxLeadB": "11-19",
  "minutoActual": 1,
  "isLive": false
}