{
  "DefensiveReboundsA": 26,
  "OffensiveReboundsB": 9,
  "OffensiveReboundsA": 10,
  "DefensiveReboundsB": 25,
  "TurnoversStartersA": 8,
  "TurnoversBenchA": 5,
  "TurnoversStartersB": 6,
  "TurnoversBenchB": 5,
  "StealsStartersA": 4,
  "StealsBenchA": 1,
  "StealsStartersB": 3,
  "StealsBenchB": 4,
  "AssistsStartersA": 14,
  "AssistsBenchA": 6,
  "AssistsStartersB": 13,
  "AssistsBenchB": 13,
  "PointsStartersA": 70,
  "PointsBenchA": 22,
  "PointsStartersB": 45,
  "PointsBenchB": 52,
  "maxA": 13,
  "minutePrevA": 19,
  "prevA": "35-51",
  "minuteStrA": 23,
  "strA": "48-51",
  "maxB": 12,
  "minutePrevB": 5,
  "prevB": "12-6",
  "minuteStrB": 8,
  "strB": "12-18",
  "maxLeadA": 6,
  "maxLeadB": 16,
  "minuteMaxLeadA": 5,
  "minuteMaxLeadB": 19,
  "puntosMaxLeadA": "12-6",
  "puntosMaxLeadB": "35-51",
  "minutoActual": 1,
  "isLive": false
}