{
  "Live": false,
  "Round": "37",
  "Date": "24/04/2024",
  "Hour": "19:00 ",
  "Stadium": "SALLE GASTON MEDECIN",
  "Capacity": "4777",
  "TeamA": "AS MONACO",
  "TeamB": "FENERBAHCE BEKO ISTANBUL",
  "CodeTeamA": "MCO",
  "TVCodeA": "ASM",
  "CodeTeamB": "ULK",
  "TVCodeB": "FBB",
  "imA": "MCO       ",
  "imB": "ULK       ",
  "ScoreA": "91",
  "ScoreB": "95",
  "CoachA": "OBRADOVIC, SASA",
  "CoachB": "JASIKEVICIUS, SARAS",
  "GameTime": "45:00",
  "RemainingPartialTime": "00:00",
  "wid": "90",
  "Quarter": "",
  "FoultsA": "27",
  "FoultsB": "27",
  "TimeoutsA": "5",
  "TimeoutsB": "5",
  "ScoreQuarter1A": 26,
  "ScoreQuarter2A": 46,
  "ScoreQuarter3A": 61,
  "ScoreQuarter4A": 81,
  "ScoreExtraTimeA": 91,
  "ScoreQuarter1B": 15,
  "ScoreQuarter2B": 37,
  "ScoreQuarter3B": 60,
  "ScoreQuarter4B": 81,
  "ScoreExtraTimeB": 95,
  "Phase": "PLAYOFFS",
  "PhaseReducedName": "P ",
  "Competition": "EUROLEAGUE 2023-24",
  "CompetitionReducedName": "E2023     ",
  "pcom": "E2023     ",
  "Referee1": "PEREZ, MIGUEL ANGEL",
  "Referee2": "PASTUSIAK, PIOTR",
  "Referee3": "SUKYS, ARTURAS"
}