{
  "Live": false,
  "Round": "16",
  "Date": "21/12/2023",
  "Hour": "20:45 ",
  "Stadium": "WIZINK CENTER",
  "Capacity": "9563",
  "TeamA": "REAL MADRID",
  "TeamB": "PARTIZAN MOZZART BET BELGRADE",
  "CodeTeamA": "MAD",
  "TVCodeA": "RMB",
  "CodeTeamB": "PAR",
  "TVCodeB": "PAR",
  "imA": "MAD       ",
  "imB": "PAR       ",
  "ScoreA": "91",
  "ScoreB": "75",
  "CoachA": "MATEO, CHUS",
  "CoachB": "OBRADOVIC, ZELJKO",
  "GameTime": "40:00",
  "RemainingPartialTime": "00:00",
  "wid": "80",
  "Quarter": "",
  "FoultsA": "14",
  "FoultsB": "20",
  "TimeoutsA": "1",
  "TimeoutsB": "5",
  "ScoreQuarter1A": 26,
  "ScoreQuarter2A": 48,
  "ScoreQuarter3A": 76,
  "ScoreQuarter4A": 91,
  "ScoreExtraTimeA": 0,
  "ScoreQuarter1B": 19,
  "ScoreQuarter2B": 36,
  "ScoreQuarter3B": 51,
  "ScoreQuarter4B": 75,
  "ScoreExtraTimeB": 0,
  "Phase": "REGULAR SEASON",
  "PhaseReducedName": "R S ",
  "Competition": "EUROLEAGUE 2023-24",
  "CompetitionReducedName": "E2023     ",
  "pcom": "E2023     ",
  "Referee1": "LOTTERMOSER, ROBERT",
  "Referee2": "BISSANG, JOSEPH",
  "Referee3": "KONSTANTINOVS, KRISTAPS"
}