{
  "Live": false,
  "Round": "32",
  "Date": "29/03/2024",
  "Hour": "18:45 ",
  "Stadium": "ULKER SPORTS AND EVENT HALL",
  "Capacity": "10781",
  "TeamA": "FENERBAHCE BEKO ISTANBUL",
  "TeamB": "ALBA BERLIN",
  "CodeTeamA": "ULK",
  "TVCodeA": "FBB",
  "CodeTeamB": "BER",
  "TVCodeB": "BER",
  "imA": "ULK       ",
  "imB": "BER       ",
  "ScoreA": "103",
  "ScoreB": "68",
  "CoachA": "JASIKEVICIUS, SARAS",
  "CoachB": "GONZALEZ, ISRAEL",
  "GameTime": "40:00",
  "RemainingPartialTime": "00:00",
  "wid": "80",
  "Quarter": "",
  "FoultsA": "17",
  "FoultsB": "25",
  "TimeoutsA": "2",
  "TimeoutsB": "2",
  "ScoreQuarter1A": 34,
  "ScoreQuarter2A": 52,
  "ScoreQuarter3A": 83,
  "ScoreQuarter4A": 103,
  "ScoreExtraTimeA": 0,
  "ScoreQuarter1B": 18,
  "ScoreQuarter2B": 40,
  "ScoreQuarter3B": 53,
  "ScoreQuarter4B": 68,
  "ScoreExtraTimeB": 0,
  "Phase": "REGULAR SEASON",
  "PhaseReducedName": "R S ",
  "Competition": "EUROLEAGUE 2023-24",
  "CompetitionReducedName": "E2023     ",
  "pcom": "E2023     ",
  "Referee1": "JOVCIC, MILIVOJE",
  "Referee2": "VILIUS, GYTIS",
  "Referee3": "UDYANSKYY, EDUARD"
}