{
  "DefensiveReboundsA": 21,
  "OffensiveReboundsB": 14,
  "OffensiveReboundsA": 12,
  "DefensiveReboundsB": 29,
  "TurnoversStartersA": 6,
  "TurnoversBenchA": 8,
  "TurnoversStartersB": 6,
  "TurnoversBenchB": 7,
  "StealsStartersA": 6,
  "StealsBenchA": 1,
  "StealsStartersB": 3,
  "StealsBenchB": 4,
  "AssistsStartersA": 10,
  "AssistsBenchA": 5,
  "AssistsStartersB": 8,
  "AssistsBenchB": 9,
  "PointsStartersA": 33,
  "PointsBenchA": 35,
  "PointsStartersB": 38,
  "PointsBenchB": 38,
  "maxA": 8,
  "minutePrevA": 22,
  "prevA": "45-44",
  "minuteStrA": 24,
  "strA": "53-44",
  "maxB": 10,
  "minutePrevB": 33,
  "prevB": "64-59",
  "minuteStrB": 37,
  "strB": "64-69",
  "maxLeadA": 10,
  "maxLeadB": 8,
  "minuteMaxLeadA": 28,
  "minuteMaxLeadB": 40,
  "puntosMaxLeadA": "62-52",
  "puntosMaxLeadB": "68-76",
  "minutoActual": 1,
  "isLive": false
}