{
  "DefensiveReboundsA": 25,
  "OffensiveReboundsB": 12,
  "OffensiveReboundsA": 10,
  "DefensiveReboundsB": 28,
  "TurnoversStartersA": 6,
  "TurnoversBenchA": 1,
  "TurnoversStartersB": 4,
  "TurnoversBenchB": 0,
  "StealsStartersA": 2,
  "StealsBenchA": 1,
  "StealsStartersB": 2,
  "StealsBenchB": 0,
  "AssistsStartersA": 6,
  "AssistsBenchA": 3,
  "AssistsStartersB": 17,
  "AssistsBenchB": 6,
  "PointsStartersA": 47,
  "PointsBenchA": 29,
  "PointsStartersB": 62,
  "PointsBenchB": 26,
  "maxA": 7,
  "minutePrevA": 9,
  "prevA": "6-10",
  "minuteStrA": 10,
  "strA": "13-10",
  "maxB": 16,
  "minutePrevB": 27,
  "prevB": "54-52",
  "minuteStrB": 30,
  "strB": "54-68",
  "maxLeadA": 5,
  "maxLeadB": 17,
  "minuteMaxLeadA": 3,
  "minuteMaxLeadB": 33,
  "puntosMaxLeadA": "5-0",
  "puntosMaxLeadB": "56-73",
  "minutoActual": 1,
  "isLive": false
}