{
  "DefensiveReboundsA": 23,
  "OffensiveReboundsB": 11,
  "OffensiveReboundsA": 11,
  "DefensiveReboundsB": 20,
  "TurnoversStartersA": 6,
  "TurnoversBenchA": 5,
  "TurnoversStartersB": 7,
  "TurnoversBenchB": 5,
  "StealsStartersA": 3,
  "StealsBenchA": 4,
  "StealsStartersB": 3,
  "StealsBenchB": 1,
  "AssistsStartersA": 16,
  "AssistsBenchA": 2,
  "AssistsStartersB": 9,
  "AssistsBenchB": 8,
  "PointsStartersA": 52,
  "PointsBenchA": 33,
  "PointsStartersB": 60,
  "PointsBenchB": 22,
  "maxA": 7,
  "minutePrevA": 14,
  "prevA": "17-23",
  "minuteStrA": 15,
  "strA": "24-23",
  "maxB": 10,
  "minutePrevB": 8,
  "prevB": "12-10",
  "minuteStrB": 11,
  "strB": "12-20",
  "maxLeadA": 7,
  "maxLeadB": 12,
  "minuteMaxLeadA": 5,
  "minuteMaxLeadB": 25,
  "puntosMaxLeadA": "10-3",
  "puntosMaxLeadB": "40-52",
  "minutoActual": 1,
  "isLive": false
}